sdid/__init__.py
sdid/core.py
sdid/py.typed
sdid-0.3.5.dist-info/METADATA
sdid-0.3.5.dist-info/WHEEL
sdid-0.3.5.dist-info/licenses/LICENSE
sdid-0.3.5.dist-info/RECORD
