Metadata-Version: 2.4
Name: sdid
Version: 0.3.5
Summary: Synthetic Difference-in-Differences (SDID) for causal inference in Python
Project-URL: Homepage, https://github.com/AluminumShark/Synthetic_Difference_in_Difference
Project-URL: Documentation, https://github.com/AluminumShark/Synthetic_Difference_in_Difference/blob/main/README.md
Project-URL: Repository, https://github.com/AluminumShark/Synthetic_Difference_in_Difference
Project-URL: Issues, https://github.com/AluminumShark/Synthetic_Difference_in_Difference/issues
Project-URL: Changelog, https://github.com/AluminumShark/Synthetic_Difference_in_Difference/releases/tag/SDID
Author-email: Levi <daiyublossom@gmail.com>
Maintainer-email: Levi <daiyublossom@gmail.com>
License: MIT
License-File: LICENSE
Keywords: causal-inference,difference-in-differences,econometrics,panel-data,sdid,synthetic-control,treatment-effect
Classifier: Development Status :: 4 - Beta
Classifier: Intended Audience :: Developers
Classifier: Intended Audience :: Science/Research
Classifier: License :: OSI Approved :: MIT License
Classifier: Operating System :: OS Independent
Classifier: Programming Language :: Python :: 3
Classifier: Programming Language :: Python :: 3.10
Classifier: Programming Language :: Python :: 3.11
Classifier: Programming Language :: Python :: 3.12
Classifier: Programming Language :: Python :: 3.13
Classifier: Topic :: Scientific/Engineering
Classifier: Topic :: Scientific/Engineering :: Mathematics
Classifier: Typing :: Typed
Requires-Python: >=3.10
Requires-Dist: cvxpy>=1.4.0
Requires-Dist: joblib>=1.3.0
Requires-Dist: matplotlib>=3.7.0
Requires-Dist: numpy>=1.24.0
Requires-Dist: pandas>=2.0.0
Requires-Dist: scipy>=1.11.0
Requires-Dist: statsmodels>=0.14.0
Provides-Extra: dev
Requires-Dist: pytest-cov>=4.0.0; extra == 'dev'
Requires-Dist: pytest>=8.0.0; extra == 'dev'
Requires-Dist: ruff>=0.8.0; extra == 'dev'
